iching/__init__.py
iching/data.json
iching/iching.py
SaltIching-0.6.dist-info/LICENSE
SaltIching-0.6.dist-info/METADATA
SaltIching-0.6.dist-info/WHEEL
SaltIching-0.6.dist-info/entry_points.txt
SaltIching-0.6.dist-info/top_level.txt
SaltIching-0.6.dist-info/RECORD
