Metadata-Version: 2.1
Name: SaltIching
Version: 0.6
Summary: A python package for Iching
Home-page: https://github.com/royalsaltmerchant/salt-iching
Author: Royal Salt Merchant
Author-email: jumpingafterrain@gmail.com
License: MIT
Platform: UNKNOWN
